pvcheetahdemo/LICENSE
pvcheetahdemo/cheetah_demo_file.py
pvcheetahdemo/cheetah_demo_mic.py
pvcheetahdemo-3.0.0.dist-info/METADATA
pvcheetahdemo-3.0.0.dist-info/WHEEL
pvcheetahdemo-3.0.0.dist-info/entry_points.txt
pvcheetahdemo-3.0.0.dist-info/top_level.txt
pvcheetahdemo-3.0.0.dist-info/RECORD
